office_templates/__init__.py
office_templates/dummy_render.py
office_templates/office_renderer/__init__.py
office_templates/office_renderer/charts.py
office_templates/office_renderer/constants.py
office_templates/office_renderer/context_extractor.py
office_templates/office_renderer/exceptions.py
office_templates/office_renderer/images.py
office_templates/office_renderer/paragraphs.py
office_templates/office_renderer/render.py
office_templates/office_renderer/tables.py
office_templates/office_renderer/utils.py
office_templates/office_renderer/pptx/__init__.py
office_templates/office_renderer/pptx/compose.py
office_templates/office_renderer/pptx/graph_processing.py
office_templates/office_renderer/pptx/layouts.py
office_templates/office_renderer/pptx/loops.py
office_templates/office_renderer/pptx/render.py
office_templates/office_renderer/pptx/utils.py
office_templates/office_renderer/xlsx/__init__.py
office_templates/office_renderer/xlsx/render.py
office_templates/office_renderer/xlsx/utils.py
office_templates/office_renderer/xlsx/worksheets.py
office_templates/templating/__init__.py
office_templates/templating/core.py
office_templates/templating/exceptions.py
office_templates/templating/formatting.py
office_templates/templating/list.py
office_templates/templating/parse.py
office_templates/templating/permissions.py
office_templates/templating/resolve.py
office_templates-0.5.2.dist-info/METADATA
office_templates-0.5.2.dist-info/WHEEL
office_templates-0.5.2.dist-info/top_level.txt
office_templates-0.5.2.dist-info/RECORD
