Metadata-Version: 2.4
Name: office-templates
Version: 0.5.2
Summary: Generates Office documents (PPTX/XLSX) from template files that are flexibly populated or composed using provided context.
Project-URL: Homepage, https://github.com/gaussian/python-office-templates
Project-URL: Issues, https://github.com/gaussian/python-office-templates/issues
Requires-Python: >=3.12
Requires-Dist: python-pptx<2,>=1
Provides-Extra: xlsx
Requires-Dist: openpyxl<4,>=3; extra == "xlsx"
